stochproc/__init__.py
stochproc/birth_death_processes/__init__.py
stochproc/birth_death_processes/birth_death_gen.py
stochproc/birth_death_processes/cad_sim.py
stochproc/birth_death_processes/cad_simulator.py
stochproc/birth_death_processes/k_of_n.py
stochproc/birth_death_processes/k_of_n_sim.py
stochproc/birth_death_processes/reliability/__init__.py
stochproc/birth_death_processes/reliability/fiji_repair_process.py
stochproc/birth_death_processes/reliability/k_of_n.py
stochproc/birth_death_processes/reliability/l_pod_k_of_n.py
stochproc/birth_death_processes/reliability/machinerepair.py
stochproc/birth_death_processes/reliability/series_parallel.py
stochproc/birth_death_processes/reliability/simulation.py
stochproc/birth_death_processes/reliability/spare_racks.py
stochproc/birth_death_processes/reliability/system_interruption_rate.py
stochproc/competitivecointoss/__init__.py
stochproc/competitivecointoss/bigmarkov.py
stochproc/competitivecointoss/gamblersruin.py
stochproc/competitivecointoss/simulation.py
stochproc/competitivecointoss/smallmarkov.py
stochproc/count_distributions/__init__.py
stochproc/count_distributions/binom.py
stochproc/count_distributions/compound_poisson.py
stochproc/count_distributions/interarrival_weibull.py
stochproc/count_distributions/negative_binomial.py
stochproc/count_distributions/poisson.py
stochproc/hypothesis/__init__.py
stochproc/hypothesis/binom_test.py
stochproc/hypothesis/hypoth_tst_simulator.py
stochproc/hypothesis/naive_binned_test.py
stochproc/hypothesis/neg_binom_tst.py
stochproc/hypothesis/poisson_test.py
stochproc/hypothesis/rate.py
stochproc/hypothesis/rate_test.py
stochproc/markov_chains/__init__.py
stochproc/markov_chains/markov_chains.py
stochproc/point_processes/__init__.py
stochproc/point_processes/auto_correlation.py
stochproc/point_processes/correlation.py
stochproc/point_processes/expon_bias.py
stochproc/point_processes/rate_simulation.py
stochproc/point_processes/renewal.py
stochproc-0.0.10.dist-info/METADATA
stochproc-0.0.10.dist-info/WHEEL
stochproc-0.0.10.dist-info/top_level.txt
stochproc-0.0.10.dist-info/RECORD
