Metadata-Version: 2.1
Name: stochproc
Version: 0.0.10
Summary: Methods to model all kinds of stochastic processes.
Home-page: https://github.com/ryu577/stochproc
Author: Rohit Pandey
Author-email: rohitpandey576@gmail.com
License: MIT
Platform: UNKNOWN
